optimizer.cpython-312-x86_64-linux-gnu.so
drawtetrado/__init__.py
drawtetrado/main.py
drawtetrado/structure.py
drawtetrado/svg_painter.py
drawtetrado-1.6.0.dist-info/METADATA
drawtetrado-1.6.0.dist-info/WHEEL
drawtetrado-1.6.0.dist-info/entry_points.txt
drawtetrado-1.6.0.dist-info/top_level.txt
drawtetrado-1.6.0.dist-info/RECORD
drawtetrado-1.6.0.dist-info/licenses/LICENSE
