Metadata-Version: 2.4
Name: drawtetrado
Version: 1.6.0
Summary: Draw simplified, layer diagrams of quadruplexes.
Home-page: https://github.com/michal-zurkowski/drawtetrado
Author: Michal Zurkowski
Author-email: michal.zurkowski@cs.put.poznan.pl
Project-URL: Bug Tracker, https://github.com/michal-zurkowski/drawtetrado/issues
Classifier: Development Status :: 5 - Production/Stable
Classifier: Environment :: Console
Classifier: Intended Audience :: Science/Research
Classifier: License :: OSI Approved :: MIT License
Classifier: Operating System :: OS Independent
Classifier: Programming Language :: Python :: 3
Classifier: Topic :: Scientific/Engineering :: Bio-Informatics
Requires-Python: >3.12
License-File: LICENSE
Requires-Dist: pycairo
Requires-Dist: svgwrite
Requires-Dist: orjson
Requires-Dist: eltetrado>=1.7.0
Requires-Dist: rnapolis
Dynamic: author
Dynamic: author-email
Dynamic: classifier
Dynamic: description
Dynamic: description-content-type
Dynamic: home-page
Dynamic: license-file
Dynamic: project-url
Dynamic: requires-dist
Dynamic: requires-python
Dynamic: summary
